{
    "summary": {
        "BPU OPs per frame (effective)": 21481830400,
        "BPU OPs per run (effective)": 21481830400,
        "BPU PE number": 1,
        "BPU core number": 1,
        "BPU march": "B25E",
        "DDR bytes per frame": 43627056,
        "DDR bytes per run": 43627056,
        "DDR bytes per second": 2999298764,
        "DDR megabytes per frame": 41.606,
        "DDR megabytes per run": 41.606,
        "DDR megabytes per second": 2860.4,
        "FPS": 68.75,
        "HBDK version": "3.49.14",
        "compiling options": "-f hbir -m /tmp/tmpsc665kg9/torch_jit_subgraph_0.hbir -o /tmp/tmpsc665kg9/torch_jit_subgraph_0.hbm --march bayes-e --progressbar --O3 --core-num 1 --fast --input-layout NHWC --output-layout NHWC --input-source pyramid",
        "frame per run": 1,
        "frame per second": 68.75,
        "input features": [
            [
                "input name",
                "input size"
            ],
            [
                "images",
                "1x640x640x3"
            ]
        ],
        "interval computing unit utilization": [
            0.86,
            0.782,
            0.885,
            0.9,
            0.889,
            0.754,
            0.898,
            0.886,
            0.839,
            0.856,
            0.911,
            0.815,
            0.78,
            0.917,
            0.993,
            0.992,
            0.844,
            0.976,
            0.986,
            0.988,
            0.822,
            0.93,
            0.904,
            0.835,
            0.777,
            0.802,
            0.716,
            0.963,
            0.844,
            0.068
        ],
        "interval computing units utilization": [
            0.86,
            0.782,
            0.885,
            0.9,
            0.889,
            0.754,
            0.898,
            0.886,
            0.839,
            0.856,
            0.911,
            0.815,
            0.78,
            0.917,
            0.993,
            0.992,
            0.844,
            0.976,
            0.986,
            0.988,
            0.822,
            0.93,
            0.904,
            0.835,
            0.777,
            0.802,
            0.716,
            0.963,
            0.844,
            0.068
        ],
        "interval loading bandwidth (megabytes/s)": [
            939,
            1312,
            1389,
            1093,
            1332,
            2371,
            2755,
            2584,
            2438,
            2208,
            1390,
            1012,
            887,
            407,
            694,
            760,
            1886,
            1543,
            48,
            39,
            1538,
            2363,
            2967,
            3116,
            1617,
            2386,
            3401,
            2663,
            2658,
            1637
        ],
        "interval number": 30,
        "interval storing bandwidth (megabytes/s)": [
            1946,
            1562,
            960,
            820,
            1520,
            1992,
            1548,
            1093,
            466,
            0,
            661,
            1574,
            1851,
            1220,
            282,
            0,
            0,
            0,
            0,
            0,
            0,
            391,
            1791,
            1756,
            1841,
            3750,
            3242,
            1397,
            820,
            546
        ],
        "interval time (ms)": 0.5,
        "latency (ms)": 14.55,
        "latency (ms) by segments": [
            14.546
        ],
        "latency (us)": 14545.8,
        "loaded bytes per frame": 26739248,
        "loaded bytes per run": 26739248,
        "model json CRC": "ae60b4ae",
        "model json file": "/tmp/tmpsc665kg9/torch_jit_subgraph_0.hbir",
        "model name": "torch_jit_subgraph_0",
        "model param CRC": "00000000",
        "multicore sync time (ms)": 0.0,
        "run per second": 68.75,
        "runtime version": "3.15.54.0",
        "stored bytes per frame": 16887808,
        "stored bytes per run": 16887808,
        "worst FPS": 68.75
    }
}
